composabl_core-0.19.1.dist-info/RECORD
composabl_core-0.19.1.dist-info/WHEEL
composabl_core-0.19.1.dist-info/top_level.txt
composabl_core-0.19.1.dist-info/METADATA
composabl_core/trainer_target_enum.cpython-310-darwin.so
composabl_core/trainer_base.cpython-310-darwin.so
composabl_core/__init__.cpython-310-darwin.so
composabl_core/settings.cpython-310-darwin.so
composabl_core/main.cpython-310-darwin.so
composabl_core/metrics/metrics_config.cpython-310-darwin.so
composabl_core/metrics/__init__.cpython-310-darwin.so
composabl_core/metrics/metrics.cpython-310-darwin.so
composabl_core/usb_license/usb_detection.cpython-310-darwin.so
composabl_core/usb_license/license_checker.cpython-310-darwin.so
composabl_core/usb_license/exceptions.cpython-310-darwin.so
composabl_core/usb_license/__init__.cpython-310-darwin.so
composabl_core/usb_license/license_generator.cpython-310-darwin.so
composabl_core/singletons/telemetry.cpython-310-darwin.so
composabl_core/singletons/__init__.cpython-310-darwin.so
composabl_core/singletons/telemetry_historian.cpython-310-darwin.so
composabl_core/proto/__init__.py
composabl_core/proto/composabl/__init__.py
composabl_core/proto/composabl/v1/main_pb2_grpc.py
composabl_core/proto/composabl/v1/__init__.py
composabl_core/proto/composabl/v1/main_pb2.py
composabl_core/proto/composabl/v1/composabl/v1/main_pb2_grpc.py
composabl_core/proto/composabl/v1/composabl/v1/main_pb2.py
composabl_core/config/config_util.cpython-310-darwin.so
composabl_core/config/trainer_config.cpython-310-darwin.so
composabl_core/config/trainer_env.cpython-310-darwin.so
composabl_core/config/trainer_target_kubernetes.cpython-310-darwin.so
composabl_core/config/trainer_target_docker.cpython-310-darwin.so
composabl_core/config/__init__.cpython-310-darwin.so
composabl_core/config/trainer_target_kubernetes_job.cpython-310-darwin.so
composabl_core/config/skill_config.cpython-310-darwin.so
composabl_core/config/trainer_target_v2.cpython-310-darwin.so
composabl_core/config/trainer_target_composabl.cpython-310-darwin.so
composabl_core/config/trainer_target_local.cpython-310-darwin.so
